pyranger/__init__.py
pyranger/pyranger.py
pyranger-0.3.dist-info/METADATA
pyranger-0.3.dist-info/RECORD
pyranger-0.3.dist-info/WHEEL
pyranger-0.3.dist-info/top_level.txt
