Metadata-Version: 2.1
Name: pyranger
Version: 0.3
Summary: A simple python library to integrate with ranger (https://github.com/flipkart-incubator/ranger)
Home-page: https://github.com/phaneeshn/pyranger
Author: Phaneesh Nagaraja
Author-email: phaneesh.n@gmail.com
License: UNKNOWN
Download-URL: https://github.com/phaneeshn/pyranger/archive/0.1.tar.gz
Keywords: service discovery,zookeeper,ranger
Platform: UNKNOWN
